osc_llm/__init__.py
osc_llm/__main__.py
osc_llm/llm.py
osc_llm/registry.py
osc_llm/tokenizer.py
osc_llm/utils.py
osc_llm/chat_templates/__init__.py
osc_llm/chat_templates/base.py
osc_llm/chat_templates/chatml.py
osc_llm/chat_templates/llama.py
osc_llm/models/__init__.py
osc_llm/models/base.py
osc_llm/models/qwen2.py
osc_llm/models/qwen3.py
osc_llm-0.2.5.dist-info/METADATA
osc_llm-0.2.5.dist-info/WHEEL
osc_llm-0.2.5.dist-info/entry_points.txt
osc_llm-0.2.5.dist-info/RECORD
