Metadata-Version: 2.4
Name: osc-llm
Version: 0.2.5
Summary: 轻量级大模型推理工具,专注于模型推理延迟,注重框架易用性和可拓展性。
Author-email: wangmengdi <790990241@qq.com>
Requires-Python: >=3.10
Requires-Dist: huggingface-hub
Requires-Dist: jinja2
Requires-Dist: loguru
Requires-Dist: modelscope
Requires-Dist: osc-transformers>=0.2.9
Requires-Dist: pydantic
Requires-Dist: sentencepiece
Requires-Dist: tokenizers
Provides-Extra: serve
Requires-Dist: fastapi>=0.110.2; extra == 'serve'
Requires-Dist: pydantic>=1.10.8; extra == 'serve'
Requires-Dist: uvicorn[standard]>=0.29.0; extra == 'serve'
